Workbook

Sheet Average monthly expenditure per
A1: Power BI Import
B2: Average monthly expenditure per year
B3: Country | C3: Type of expenditure/ data | D3: 2015 | E3: 2016 | F3: 2017 | G3: 2018 | H3: 2019 | I3: 2020 | J3: 2021 | K3: 2022 | L3: 2023 | M3: 2024
B4: Singapore | C4: Food And Non-Alcoholic Beverages | D4: 132.32114 | E4: 134.90161 | F4: 134.90162 | G4: 134.9 | H4: 153.21893 | I4: 152.39808 | J4: 156.138 | K4: 172.18066 | L4: 167.3 | M4: 176.19833
B5: Singapore | C5: Alcoholic Beverages And Tobacco | D5: 25.60105 | E5: 26.100312 | F5: 26.100313 | G5: 26.1 | H5: 19.232502 | I5: 19.129467 | J5: 19.598912 | K5: 21.612636 | L5: 21 | M5: 22.116945
B6: Singapore | C6: Food And Beverage Serving Services | D6: 365.37897 | E6: 372.50445 | F6: 372.50447 | G6: 372.5 | H6: 375.67487 | I6: 373.66225 | J6: 382.83207 | K6: 422.16682 | L6: 410.2 | M6: 432.01766
B7: Singapore | C7: Clothing And Footwear | D7: 58.362547 | E7: 59.500711 | F7: 59.500714 | G7: 59.5 | H7: 34.710087 | I7: 34.524132 | J7: 35.371369 | K7: 39.005661 | L7: 37.9 | M7: 39.91582
B8: Singapore | C8: Housing And Utilities | D8: 1036.1069 | E8: 1056.3126 | F8: 1056.3127 | G8: 1056.3 | H8: 1088.1017 | I8: 1082.2723 | J8: 1108.8318 | K8: 1222.7606 | L8: 1188.1 | M8: 1251.2925
B9: Singapore | C9: Furnishing, Household Equipment And Routine Household Maintenance | D9: 97.107432 | E9: 99.001183 | F9: 99.001188 | G9: 99 | H9: 109.80843 | I9: 109.22014 | J9: 111.90045 | K9: 123.39786 | L9: 119.9 | M9: 126.27722
B10: Singapore | C10: Health | D10: 129.08422 | E10: 131.60157 | F10: 131.60158 | G10: 131.6 | H10: 216.68619 | I10: 215.52532 | J10: 220.8144 | K10: 243.50236 | L10: 236.6 | M10: 249.18425
B11: Singapore | C11: Transport | D11: 318.10041 | E11: 324.30387 | F11: 324.30389 | G11: 324.3 | H11: 286.74744 | I11: 285.21124 | J11: 292.21044 | K11: 322.23411 | L11: 313.1 | M11: 329.75312
B12: Singapore | C12: Information And Communication | D12: 124.67025 | E12: 127.10152 | F12: 127.10153 | G12: 127.1 | H12: 113.47176 | I12: 112.86385 | J12: 115.63358 | K12: 127.51455 | L12: 123.9 | M12: 130.48998
B13: Singapore | C13: Recreation, Sport And Culture | D13: 158.80498 | E13: 161.90193 | F13: 161.90194 | G13: 161.9 | H13: 132.79585 | I13: 132.08441 | J13: 135.32582 | K13: 149.2301 | L13: 145 | M13: 152.71224
B14: Singapore | C14: Education | D14: 32.369144 | E14: 33.000394 | F14: 33.000396 | G14: 33 | H14: 16.393418 | I14: 16.305593 | J14: 16.705739 | K14: 18.422199 | L14: 17.9 | M14: 18.852063
B15: Singapore | C15: Accommodation Services | D15: 28.249435 | E15: 28.800344 | F15: 28.800346 | G15: 28.8 | H15: 27.841336 | I15: 27.69218 | J15: 28.371758 | K15: 31.286863 | L15: 30.4 | M15: 32.016911
... B23: Singapore | C23: Average monthly expenditure | D23: 2790.9068 | E23: 2845.334 | F23: 2845.3341 | G23: 2845.3 | H23: 2905.2984 | I23: 2889.7337 | J23: 2960.6489 | K23: 3264.8459 | L23: 3172.3 | M23: 3341.0279

Sheet Food at home and out
B2: Type of Expenditure | C2: 2015 | D2: 2016 | E2: 2017 | F2: 2018 | G2: 2019 | H2: 2020 | I2: 2021 | J2: 2022 | K2: 2023 | L2: 2024
B3: Food at home | C3: 157.92219 | D3: 161.00192 | E3: 161.00193 | F3: 161 | G3: 172.45143 | H3: 171.52755 | I3: 175.73691 | J3: 193.7933 | K3: 188.3 | L3: 198.31527
B4: Dining Outside | C4: 365.37897 | D4: 372.50445 | E4: 372.50447 | F4: 372.5 | G4: 375.67487 | H4: 373.66225 | I4: 382.83207 | J4: 422.16682 | K4: 410.2 | L4: 432.01766
B5: Other Expenditures | C5: 2267.6057 | D5: 2311.8276 | E5: 2311.8277 | F5: 2311.8 | G5: 2357.1721 | H5: 2344.5439 | I5: 2402.0799 | J5: 2648.8858 | K5: 2573.8 | L5: 2710.6949
B9: Coutry | C9: Type of Expenditure | D9: 2015 | E9: 2016 | F9: 2017 | G9: 2018 | H9: 2019 | I9: 2020 | J9: 2021 | K9: 2022 | L9: 2023 | M9: 2024
B10: Singapore | C10: Food at home | D10: 0.056584543 | E10: 0.056584543 | F10: 0.056584543 | G10: 0.056584543 | H10: 0.059357564 | I10: 0.059357564 | J10: 0.059357564 | K10: 0.059357564 | L10: 0.059357564 | M10: 0.059357564
B11: Singapore | C11: Dining Outside | D11: 0.13091765 | E11: 0.13091765 | F11: 0.13091765 | G11: 0.13091765 | H11: 0.12930681 | I11: 0.12930681 | J11: 0.12930681 | K11: 0.12930681 | L11: 0.12930681 | M11: 0.12930681
B12: Singapore | C12: Other Expenditures | D12: 0.8124978 | E12: 0.8124978 | F12: 0.8124978 | G12: 0.8124978 | H12: 0.81133562 | I12: 0.81133562 | J12: 0.81133562 | K12: 0.81133562 | L12: 0.81133562 | M12: 0.81133562

Sheet Income Growth
B2: Country | C2: Tyoe of Data | D2: 2015 | E2: 2016 | F2: 2017 | G2: 2018 | H2: 2019 | I2: 2020 | J2: 2021 | K2: 2022 | L2: 2023 | M2: 2024
B3: Singapore | C3: Income Growth | D3: 0 | E3: 0.0068635969 | F3: 0.03779446 | G3: 0.009146088 | H3: 0.020515778 | I3: -0.012191184 | J3: 0.0033510421 | K3: 0.069077876 | L3: 0.063547699 | M3: 0.041839805
B4: Singapore | C4: Food at Home Growth | D4: 0 | E4: 0.019501606 | F4: 5.3527054e-08 | G4: -1.2000645e-05 | H4: 0.071126916 | I4: -0.0053573551 | J4: 0.024540417 | K4: 0.10274673 | L4: -0.028346178 | M4: 0.053187864
B5: Singapore | C5: Dining Out Growth | D5: 0 | E5: 0.019501606 | F5: 5.3527054e-08 | G5: -1.2000645e-05 | H5: 0.0085231412 | I5: -0.0053573551 | J5: 0.024540417 | K5: 0.10274673 | L5: -0.028346178 | M5: 0.053187864
B6: Singapore | C6: Food Spending Growth | D6: 0 | E6: 0.019501606 | F6: 5.3527054e-08 | G6: -1.2000645e-05 | H6: 0.027415752 | I6: -0.0053573551 | J6: 0.024540417 | K6: 0.10274673 | L6: -0.028346178 | M6: 0.053187864
B7: Singapore | C7: Inflation | D7: 1 | E7: 0.9947 | F7: 1.0004 | G7: 1.0048 | H7: 1.0105 | I7: 1.0088 | J7: 1.0322 | K7: 1.0954 | L7: 1.1484 | M7: 1.1758
B8: Singapore | C8: Food Inflation | D8: 1 | E8: 1.0232 | F8: 1.0365 | G8: 1.05 | H8: 1.0618 | I8: 1.0924 | J8: 1.1098 | K8: 1.1683 | L8: 1.2282 | M8: 1.2433
B9: Singapore | C9: Real Spending Growth | D9: 0 | E9: 0.019059428 | F9: 5.1642117e-08 | G9: -1.1429186e-05 | H9: 0.025820072 | I9: -0.0049042064 | J9: 0.022112468 | K9: 0.087945498 | L9: -0.023079448 | M9: 0.042779589
B10: Singapore | C10: Real Income Growth | D10: 0 | E10: 0.0069001678 | F10: 0.037779349 | G10: 0.0091023965 | H10: 0.020302601 | I10: -0.012084837 | J10: 0.0032465046 | K10: 0.063061782 | L10: 0.055335858 | M10: 0.035584117

Sheet Average monthly income per year
O1: Table Purpose
B2: Average and Median Household Employment Income 2014 -2024 | O2: The table was created in order to estimate the average monthly income of Singaporeans
B3: Year | C3: 2014 | D3: 2015 | E3: 2016 | F3: 2017 | G3: 2018 | H3: 2019 | I3: 2020 | J3: 2021 | K3: 2022 | L3: 2023 | M3: 2024
B4: Average | C4: 11143 | D4: 11510 | E4: 11589 | F4: 12027 | G4: 12137 | H4: 12386 | I4: 12235 | J4: 12276 | K4: 13124 | L4: 13958 | M4: 14542
B5: Median | C5: 8292 | D5: 8666 | E5: 8846 | F5: 9023 | G5: 9293 | H5: 9425 | I5: 9189 | J5: 9520 | K5: 10099 | L5: 10869 | M5: 11297
B7: Growth Percentage of the Average Income 2015 - 2024
B8: Year | C8: 2015 | D8: 2016 | E8: 2017 | F8: 2018 | G8: 2019 | H8: 2020 | I8: 2021 | J8: 2022 | K8: 2023 | L8: 2024
B9: Value | C9: =(D4-C4)/C4 -> 0.032935475 | D9: =(E4-D4)/D4 -> 0.0068635969 | E9: =(F4-E4)/E4 -> 0.03779446 | F9: =(G4-F4)/F4 -> 0.009146088 | G9: =(H4-G4)/G4 -> 0.020515778 | H9: =(I4-H4)/H4 -> -0.012191184 | I9: =(J4-I4)/I4 -> 0.0033510421 | J9: =(K4-J4)/J4 -> 0.069077876 | ... L9: =(M4-L4)/L4 -> 0.041839805

Sheet Global Food Inflation
B2: General Inflation Index for Singaporeans Goods and Services
B3: REF_AREA_LABEL | C3: INDICATOR | D3: INDICATOR_LABEL | E3: UNIT_MEASURE | F3: UNIT_MEASURE_LABEL | G3: 2014 | H3: 2015 | I3: 2016 | J3: 2017 | K3: 2018 | L3: 2019 | M3: 2020 | N3: 2021 | O3: 2022 | P3: 2023 | Q3: 2024 | R3: Growth per year | S3: Value
B4: Singapore | C4: FAO_CP_23012 | D4: Consumer Prices, General Indices (2015 = 100) | E4: IX | F4: Index | G4: 100.53 | H4: 100 | I4: 99.47 | J4: 100.04 | K4: 100.48 | L4: 101.05 | M4: 100.88 | N4: 103.22 | O4: 109.54 | P4: 114.84 | Q4: 117.58 | R4: 2015 Growth | S4: -0.52
B5: Singapore | C5: FAO_CP_23012 | D5: Consumer Prices, General Indices (2015 = 100) | E5: IX | F5: Index | G5: 100.53 | H5: 100 | I5: 99.47 | J5: 100.04 | K5: 100.48 | L5: 101.05 | M5: 100.88 | N5: 103.22 | O5: 109.54 | P5: 114.84 | Q5: 117.58 | R5: 2016 Growth | S5: -0.53
B6: Singapore | C6: FAO_CP_23012 | D6: Consumer Prices, General Indices (2015 = 100) | E6: IX | F6: Index | G6: 100.53 | H6: 100 | I6: 99.47 | J6: 100.04 | K6: 100.48 | L6: 101.05 | M6: 100.88 | N6: 103.22 | O6: 109.54 | P6: 114.84 | Q6: 117.58 | R6: 2017 Growth | S6: 0.58
B7: Singapore | C7: FAO_CP_23012 | D7: Consumer Prices, General Indices (2015 = 100) | E7: IX | F7: Index | G7: 100.53 | H7: 100 | I7: 99.47 | J7: 100.04 | K7: 100.48 | L7: 101.05 | M7: 100.88 | N7: 103.22 | O7: 109.54 | P7: 114.84 | Q7: 117.58 | R7: 2018 Growth | S7: 0.44
B8: Singapore | C8: FAO_CP_23012 | D8: Consumer Prices, General Indices (2015 = 100) | E8: IX | F8: Index | G8: 100.53 | H8: 100 | I8: 99.47 | J8: 100.04 | K8: 100.48 | L8: 101.05 | M8: 100.88 | N8: 103.22 | O8: 109.54 | P8: 114.84 | Q8: 117.58 | R8: 2019 Growth | S8: 0.57
B9: Singapore | C9: FAO_CP_23012 | D9: Consumer Prices, General Indices (2015 = 100) | E9: IX | F9: Index | G9: 100.53 | H9: 100 | I9: 99.47 | J9: 100.04 | K9: 100.48 | L9: 101.05 | M9: 100.88 | N9: 103.22 | O9: 109.54 | P9: 114.84 | Q9: 117.58 | R9: 2020 Growth | S9: -0.17
B10: Singapore | C10: FAO_CP_23012 | D10: Consumer Prices, General Indices (2015 = 100) | E10: IX | F10: Index | G10: 100.53 | H10: 100 | I10: 99.47 | J10: 100.04 | K10: 100.48 | L10: 101.05 | M10: 100.88 | N10: 103.22 | O10: 109.54 | P10: 114.84 | Q10: 117.58 | R10: 2021 Growth | S10: 2.32
B11: Singapore | C11: FAO_CP_23012 | D11: Consumer Prices, General Indices (2015 = 100) | E11: IX | F11: Index | G11: 100.53 | H11: 100 | I11: 99.47 | J11: 100.04 | K11: 100.48 | L11: 101.05 | M11: 100.88 | N11: 103.22 | O11: 109.54 | P11: 114.84 | Q11: 117.58 | R11: 2022 Growth | S11: 6.13
B12: Singapore | C12: FAO_CP_23012 | D12: Consumer Prices, General Indices (2015 = 100) | E12: IX | F12: Index | G12: 100.53 | H12: 100 | I12: 99.47 | J12: 100.04 | K12: 100.48 | L12: 101.05 | M12: 100.88 | N12: 103.22 | O12: 109.54 | P12: 114.84 | Q12: 117.58 | R12: 2023 Growth | S12: 4.83
B13: Singapore | C13: FAO_CP_23012 | D13: Consumer Prices, General Indices (2015 = 100) | E13: IX | F13: Index | G13: 100.53 | H13: 100 | I13: 99.47 | J13: 100.04 | K13: 100.48 | L13: 101.05 | M13: 100.88 | N13: 103.22 | O13: 109.54 | P13: 114.84 | Q13: 117.58 | R13: 2024 Growth | S13: 2.39
B15: Table purpose
B16: The table is used to estimate the average monthly income of Singaporeans

Sheet Estimated expenditure growth
A1: Expenditure growth calculation
C3: Expenditure growth ≈ CPI growth + α × Income growth
B5: Year | C5: Reason | D5: Parameter Value | E5: CPI growth | F5: Income growth | G5: Expenditure growth | H5: Estimated monthly expenditure
B6: 2015 | C6: Normal pre-COVID behaviour, moderate savings | D6: 0.75 | E6: ='Global Food Inflation'!S4/100 -> -0.0052 | F6: ='Average monthly income per year'!$C9 -> 0.032935475 | G6: =E6+D6*F6 -> 0.019501606 | H6: ='Average monthly expenditure per'!E23/(1+'Estimated expenditure growth'!G6) -> 2790.9068
B7: 2016 | C7: Similar trend to 2015 | D7: 0.75 | E7: ='Global Food Inflation'!S5/100 -> -0.0053 | F7: {='Average monthly income per year'!$D$9:$D$9} -> 0.0068635969 | G7: =E7+D7*F7 -> -0.00015230235 | H7: ='Estimated expenditure growth'!H8/1+'Estimated expenditure growth'!G7 -> 2845.334
B8: 2017 | C8: Stable consumption | D8: 0.75 | E8: ='Global Food Inflation'!S6/100 -> 0.0058 | F8: {='Average monthly income per year'!$E$9:$E$9} -> 0.03779446 | G8: =E8+D8*F8 -> 0.034145845 | H8: ='Average monthly expenditure per'!G23/1+'Estimated expenditure growth'!G8 -> 2845.3341
B9: 2018 | C9: Slight caution as personal saving slightly high | D9: 0.75 | E9: ='Global Food Inflation'!S7/100 -> 0.0044 | F9: {='Average monthly income per year'!$F$9:$F$9} -> 0.009146088 | G9: =E9+D9*F9 -> 0.011259566 | H9: Real
B10: 2019 | C10: Pre-COVID, moderate expenditures | D10: 0.75 | E10: ='Global Food Inflation'!S8/100 -> 0.0057 | F10: {='Average monthly income per year'!$G$9:$G$9} -> 0.020515778 | G10: =E10+D10*F10 -> 0.021086834 | H10: =G10*'Average monthly expenditure per'!G23+'Average monthly expenditure per'!G23 -> 2905.2984
B11: 2020 | C11: COVID impact → high savings, weak spending | D11: 0.3 | E11: ='Global Food Inflation'!S9/100 -> -0.0017 | F11: {='Average monthly income per year'!$H$9:$H$9} -> -0.012191184 | G11: =E11+D11*F11 -> -0.0053573551 | H11: ='Average monthly expenditure per'!H23*'Estimated expenditure growth'!G11+'Average monthly expenditure per'!H23 -> 2889.7337
B12: 2021 | C12: Aftershock of COVID, still high savings | D12: 0.4 | E12: ='Global Food Inflation'!S10/100 -> 0.0232 | F12: {='Average monthly income per year'!$I$9:$I$9} -> 0.0033510421 | G12: =E12+D12*F12 -> 0.024540417 | H12: ='Average monthly expenditure per'!I23*'Estimated expenditure growth'!G12+'Average monthly expenditure per'!I23 -> 2960.6489
B13: 2022 | C13: Gradual reopening, consumption recovered | D13: 0.6 | E13: ='Global Food Inflation'!S11/100 -> 0.0613 | F13: {='Average monthly income per year'!$J$9:$J$9} -> 0.069077876 | G13: =E13+D13*F13 -> 0.10274673 | H13: ='Average monthly expenditure per'!J23*'Estimated expenditure growth'!G13+'Average monthly expenditure per'!J23 -> 3264.8459
B14: 2023 | C14: Households spending more but still higher saving | D14: 0.65 | E14: ='Global Food Inflation'!S12/100 -> 0.0483 | F14: {='Average monthly income per year'!$K$9:$K$9} -> 0.063547699 | G14: =E14+D14*F14 -> 0.089606004 | H14: Real
B15: 2024 | C15: Return toward normal, consumption growth rebounds | D15: 0.7 | E15: ='Global Food Inflation'!S13/100 -> 0.0239 | F15: {='Average monthly income per year'!$L$9:$L$9} -> 0.041839805 | G15: =E15+D15*F15 -> 0.053187864 | H15: =G15*'Average monthly expenditure per'!L23+'Average monthly expenditure per'!L23 -> 3341.0279

Sheet Dining Out Percentage
B2: Dining Out Percentage from the Total Food Expense
B3: Country | C3: Type of expenditure/ data | D3: 2015 | E3: 2016 | F3: 2017 | G3: 2018 | H3: 2019 | I3: 2020 | J3: 2021 | K3: 2022 | L3: 2023 | M3: 2024 | O3: Table Purpose
B4: Singapore | C4: Food And Non-Alcoholic Beverages | D4: 132.32114 | E4: 134.90161 | F4: 134.90162 | G4: 134.9 | H4: 153.21893 | I4: 152.39808 | J4: 156.138 | K4: 172.18066 | L4: 167.3 | M4: 176.19833 | O4: The table was created to find out the percentage portion of the dining out expense from the total food related expense
B5: Singapore | C5: Alcoholic Beverages And Tobacco | D5: 25.60105 | E5: 26.100312 | F5: 26.100313 | G5: 26.1 | H5: 19.232502 | I5: 19.129467 | J5: 19.598912 | K5: 21.612636 | L5: 21 | M5: 22.116945
B6: Singapore | C6: Food And Beverage Serving Services | D6: 365.37897 | E6: 372.50445 | F6: 372.50447 | G6: 372.5 | H6: 375.67487 | I6: 373.66225 | J6: 382.83207 | K6: 422.16682 | L6: 410.2 | M6: 432.01766
B7: Singapore | C7: Total Food Expense | D7: =SUM(D4:D6) -> 523.30116 | E7: =SUM(E4:E6) -> 533.50637 | F7: =SUM(F4:F6) -> 533.5064 | G7: =SUM(G4:G6) -> 533.5 | H7: =SUM(H4:H6) -> 548.1263 | I7: =SUM(I4:I6) -> 545.1898 | J7: =SUM(J4:J6) -> 558.56898 | K7: =SUM(K4:K6) -> 615.96011 | ... M7: =SUM(M4:M6) -> 630.33294
B8: Singapore | C8: Dining out portion from Total Food Expense | D8: =D6/D7 -> 0.69821931 | E8: =E6/E7 -> 0.69821931 | F8: =F6/F7 -> 0.69821931 | G8: =G6/G7 -> 0.69821931 | H8: =H6/H7 -> 0.68538012 | I8: =I6/I7 -> 0.68538012 | J8: =J6/J7 -> 0.68538012 | K8: =K6/K7 -> 0.68538012 | ... M8: =M6/M7 -> 0.68538012

Sheet Data Type
B2: Country | C2: Data Type | D2: Year | E2: Data Acquisition Method
B3: Singapore | C3: Average monthly income | D3: 2015 | E3: Calculated Estimation
B4: Singapore | C4: Average monthly income | D4: 2016 | E4: Calculated Estimation
B5: Singapore | C5: Average monthly income | D5: 2017 | E5: Calculated Estimation
B6: Singapore | C6: Average monthly income | D6: 2018 | E6: Real source
B7: Singapore | C7: Average monthly income | D7: 2019 | E7: Calculated Estimation
B8: Singapore | C8: Average monthly income | D8: 2020 | E8: Calculated Estimation
B9: Singapore | C9: Average monthly income | D9: 2021 | E9: Calculated Estimation
B10: Singapore | C10: Average monthly income | D10: 2022 | E10: Calculated Estimation
B11: Singapore | C11: Average monthly income | D11: 2023 | E11: Real source
B12: Singapore | C12: Average monthly income | D12: 2024 | E12: Calculated Estimation
